SageLogger/Logger.py
SageLogger/SageException.py
SageLogger/SageFactory.py
SageLogger/__init__.py
SageLogger-1.7.dist-info/METADATA
SageLogger-1.7.dist-info/WHEEL
SageLogger-1.7.dist-info/top_level.txt
SageLogger-1.7.dist-info/RECORD
