Metadata-Version: 2.1
Name: SageLogger
Version: 1.7
Summary: Yet another python logger, or is it like any other?
Home-page: https://github.com/PanSageYT/SageLogger
Author: PanSage_
Author-email: root@pansage.xyz
Classifier: Programming Language :: Python :: 3
Classifier: License :: OSI Approved :: MIT License
Classifier: Operating System :: OS Independent
Requires-Python: >=3.7
Requires-Dist: colorama
Requires-Dist: requests
